yolo_overlay/__init__.py
yolo_overlay/detection.py
yolo_overlay/overlay.py
yolo_overlay/utils.py
yolo_overlay/resources/overlay-yolo.dll
yolo_overlay/resources/writing50e11n.pt
yolo_overlay/tests/__init__.py
yolo_overlay/tests/test_overlay.py
yolo_overlay-0.1.2.dist-info/METADATA
yolo_overlay-0.1.2.dist-info/WHEEL
yolo_overlay-0.1.2.dist-info/entry_points.txt
yolo_overlay-0.1.2.dist-info/top_level.txt
yolo_overlay-0.1.2.dist-info/RECORD
