Metadata-Version: 2.1
Name: yolo-overlay
Version: 0.1.2
Summary: A Python package to overlay YOLO detections on displays using a custom DLL.
Home-page: https://github.com/wuhplaptop/yolo_overlay
Author: wuhp
Author-email: your.email@example.com
License: UNKNOWN
Keywords: yolo overlay detection computer-vision
Platform: UNKNOWN
Classifier: Programming Language :: Python :: 3
Classifier: Operating System :: Microsoft :: Windows
Classifier: License :: OSI Approved :: MIT License
Classifier: Topic :: Software Development :: Libraries :: Python Modules
Requires-Python: >=3.7
Requires-Dist: Pillow>=9.4.0
Requires-Dist: mss>=6.1.0
Requires-Dist: ultralytics>=8.0.49
Requires-Dist: screeninfo>=0.8.1
Requires-Dist: numpy>=1.24.3
Requires-Dist: requests>=2.25.1
